Metadata-Version: 1.0
Name: Gpt-Client
Version: 1.28
Summary: A Python script to communicate with big text AI models (like gpt4 or OpenChat)
Home-page: UNKNOWN
Author: Anybodyy
Author-email: polnyjloh76@gmail.com
License: MIT
Platform: UNKNOWN
